<?xml version="1.0" encoding="UTF-8" standalone="yes"?>
<worksheet xmlns="http://schemas.openxmlformats.org/spreadsheetml/2006/main" xmlns:r="http://schemas.openxmlformats.org/officeDocument/2006/relationships" xmlns:mc="http://schemas.openxmlformats.org/markup-compatibility/2006" mc:Ignorable="x14ac" xmlns:x14ac="http://schemas.microsoft.com/office/spreadsheetml/2009/9/ac"><sheetPr codeName="Sheet20"/><dimension ref="A1:C560"/><sheetViews><sheetView showGridLines="0" topLeftCell="A468" workbookViewId="0"><selection activeCell="A465" sqref="A465"/></sheetView></sheetViews><sheetFormatPr defaultRowHeight="15"/><cols><col min="1" max="1" width="69.85546875" style="294" customWidth="1"/><col min="2" max="2" width="85" style="365" customWidth="1"/><col min="3" max="16384" width="9.140625" style="294"/></cols><sheetData><row r="1" spans="1:2"><c r="A1" s="294" t="s"><v>3361</v></c><c r="B1" s="365" t="s"><v>1787</v></c></row><row r="2" spans="1:2"><c r="A2" s="294" t="s"><v>3380</v></c><c r="B2" s="365" t="s"><v>1788</v></c></row><row r="14" spans="1:2" ht="15.75" thickBot="1"><c r="A14" s="352" t="str"><f>Translation!B101</f><v>Type</v></c></row><row r="15" spans="1:2" ht="208.5" customHeight="1" thickTop="1"><c r="A15" s="913" t="str"><f>Translation!B92</f><v>Fixture technology used - high pressure sodium (HPS) or Light Emitting Diode (LED). The value is for reference, and for use in determining default fixture and bulb costs and lamp lumen depreciation. Other lamp types (low pressure sodium, metal halide, etc) can be defined in either category if assumptions of cost and life are adjusted appropriately</v></c><c r="B15" s="913"/></row><row r="30" spans="1:2" ht="15.75" thickBot="1"><c r="A30" s="352" t="str"><f>Translation!B102</f><v>Watts</v></c></row><row r="31" spans="1:2" s="350" customFormat="1" ht="47.25" customHeight="1" thickTop="1"><c r="A31" s="913" t="str"><f>Translation!B100</f><v xml:space="preserve">This is actual power consumption of the fixture, including the bulb and any ballast or other electronics. It is read in from the IES file when other fixture data is captured. </v></c><c r="B31" s="913"/></row><row r="33" spans="1:2" ht="151.5" customHeight="1"><c r="A33" s="913" t="str"><f>Translation!B97</f><v xml:space="preserve">Note that some manufacturers don't follow proper format when providing the power and don't include the ballast power. Therefore, it's very important to check the wattage assumptions when adding a fixture. One indication that a fixture doesn't include the ballast is if the watts are the same as the nominal wattage for that fixture (e.g. 150 watts for a 150 watt fixture) - actual power including ballast is usually higher. LED fixtures don't measure bulb power separately and will usually be correct. </v></c><c r="B33" s="913"/></row><row r="52" spans="1:2" ht="15.75" thickBot="1"><c r="A52" s="353" t="str"><f>Translation!B95</f><v>Total Light Loss Factor</v></c></row><row r="53" spans="1:2" ht="258.75" customHeight="1" thickTop="1"><c r="A53" s="913" t="str"><f>Translation!B96</f><v xml:space="preserve">Light loss factor is the ratio of design condition light output to initial light output. This includes Lamp Lumen Depreciation (LLD), Luminaire Dirt Depreciation (LDD), and Temperature Effects. As a lamp ages, it produces less light than it did initially; different fixtures may also change at different rates. Lighting design should be done to the level that the lamp will be at end of life, rather than at the beginning. You may need to adjust the dirt depreciation assumption for your location; lamp lumen depreciation should be tied to the assumed fixture life. </v></c><c r="B53" s="913"/></row><row r="54" spans="1:2"><c r="A54" s="365"/></row><row r="55" spans="1:2"><c r="A55" s="365"/></row><row r="56" spans="1:2"><c r="A56" s="365"/></row><row r="57" spans="1:2"><c r="A57" s="365"/></row><row r="58" spans="1:2"><c r="A58" s="365"/></row><row r="59" spans="1:2"><c r="A59" s="365"/></row><row r="60" spans="1:2"><c r="A60" s="365"/></row><row r="61" spans="1:2"><c r="A61" s="365"/></row><row r="62" spans="1:2"><c r="A62" s="365"/></row><row r="63" spans="1:2"><c r="A63" s="365"/></row><row r="64" spans="1:2"><c r="A64" s="365"/></row><row r="65" spans="1:2"><c r="A65" s="365"/></row><row r="66" spans="1:2"><c r="A66" s="365"/></row><row r="67" spans="1:2" ht="15.75" thickBot="1"><c r="A67" s="353" t="str"><f>Translation!B88</f><v>Ballast Factor</v></c></row><row r="68" spans="1:2" ht="353.25" customHeight="1" thickTop="1"><c r="A68" s="913" t="str"><f>Translation!B94</f><v xml:space="preserve">If the actual ballast used in a lamp differs from the standard reference ballast used for photometric testing, the lamp may produce more or less light; this factor adjusts the photometric data for a lamp up or down if a different ballast is to be used. </v></c><c r="B68" s="913"/></row><row r="69" spans="1:2"><c r="A69" s="913"/><c r="B69" s="913"/></row><row r="70" spans="1:2"><c r="A70" s="689"/><c r="B70" s="689"/></row><row r="71" spans="1:2"><c r="A71" s="689"/><c r="B71" s="689"/></row><row r="72" spans="1:2"><c r="A72" s="689"/><c r="B72" s="689"/></row><row r="73" spans="1:2"><c r="A73" s="689"/><c r="B73" s="689"/></row><row r="74" spans="1:2"><c r="A74" s="689"/><c r="B74" s="689"/></row><row r="75" spans="1:2" ht="15.75" thickBot="1"><c r="A75" s="352" t="str"><f>Translation!B324</f><v>Installation Cost ($/fixture)</v></c><c r="B75" s="689"/></row><row r="76" spans="1:2" ht="290.25" customHeight="1" thickTop="1"><c r="A76" s="914" t="str"><f>Translation!B325</f><v>The installation cost should be the all-in cost for installing the fixture, including street closure costs, labor costs, etc. as relevant. If this is your baseline fixture (i.e. already installed), this cost should be zero</v></c><c r="B76" s="914"/></row><row r="77" spans="1:2" ht="104.25" customHeight="1"><c r="A77" s="688"/><c r="B77" s="688"/></row><row r="78" spans="1:2"><c r="A78" s="688"/><c r="B78" s="688"/></row><row r="79" spans="1:2"><c r="A79" s="688"/><c r="B79" s="688"/></row><row r="80" spans="1:2" ht="15.75" thickBot="1"><c r="A80" s="352" t="str"><f>Translation!B326</f><v>Energy Cost</v></c></row><row r="81" spans="1:3" ht="182.25" customHeight="1" thickTop="1"><c r="A81" s="914" t="str"><f>Translation!B327</f><v xml:space="preserve">Enter the average cost of electricity that will be paid over the life of the fixture. If you wish to include energy cost increase assumptions, this should be done manually and entered as the average cost over the analysis period in today's currency. 
</v></c><c r="B81" s="914"/><c r="C81" s="594"/></row><row r="82" spans="1:3"><c r="A82" s="688"/><c r="B82" s="688"/><c r="C82" s="594"/></row><row r="83" spans="1:3"><c r="A83" s="688"/><c r="B83" s="688"/><c r="C83" s="594"/></row><row r="84" spans="1:3"><c r="A84" s="688"/><c r="B84" s="688"/><c r="C84" s="594"/></row><row r="85" spans="1:3"><c r="A85" s="688"/><c r="B85" s="688"/><c r="C85" s="594"/></row><row r="86" spans="1:3"><c r="A86" s="688"/><c r="B86" s="688"/><c r="C86" s="594"/></row><row r="87" spans="1:3" ht="15.75" thickBot="1"><c r="A87" s="352" t="str"><f>Translation!B328</f><v>Discount Rate</v></c></row><row r="88" spans="1:3" ht="145.5" customHeight="1" thickTop="1"><c r="A88" s="915" t="str"><f>Translation!B329</f><v xml:space="preserve">Enter the assumed discount rate for calculating the net present value of future energy and maintenance cost savings
</v></c><c r="B88" s="915"/></row><row r="89" spans="1:3"><c r="A89" s="690"/><c r="B89" s="690"/></row><row r="90" spans="1:3"><c r="A90" s="690"/><c r="B90" s="690"/></row><row r="91" spans="1:3"><c r="A91" s="690"/><c r="B91" s="690"/></row><row r="92" spans="1:3" ht="75.75" customHeight="1"><c r="A92" s="690"/><c r="B92" s="690"/></row><row r="93" spans="1:3" ht="15.75" thickBot="1"><c r="A93" s="352" t="str"><f>Translation!B330</f><v>Analysis Period</v></c></row><row r="94" spans="1:3" ht="172.5" customHeight="1" thickTop="1"><c r="A94" s="914" t="str"><f>Translation!B331</f><v xml:space="preserve">Enter the time period over which you'd like to evaluate the differences in maintenance, bulb replacement, and energy costs between the scenarios
</v></c><c r="B94" s="914"/></row><row r="95" spans="1:3"><c r="A95" s="688"/><c r="B95" s="688"/></row><row r="96" spans="1:3"><c r="A96" s="688"/><c r="B96" s="688"/></row><row r="97" spans="1:2"><c r="A97" s="688"/><c r="B97" s="688"/></row><row r="98" spans="1:2"><c r="A98" s="688"/><c r="B98" s="688"/></row><row r="99" spans="1:2"><c r="A99" s="688"/><c r="B99" s="688"/></row><row r="100" spans="1:2"><c r="A100" s="688"/><c r="B100" s="688"/></row><row r="101" spans="1:2"><c r="A101" s="688"/><c r="B101" s="688"/></row><row r="102" spans="1:2" ht="78.75" customHeight="1"><c r="A102" s="688"/><c r="B102" s="688"/></row><row r="103" spans="1:2" ht="15.75" thickBot="1"><c r="A103" s="352" t="str"><f>Translation!B89</f><v>Fixture Cost</v></c></row><row r="104" spans="1:2" ht="119.25" customHeight="1" thickTop="1"><c r="A104" s="913" t="str"><f>Translation!B98</f><v xml:space="preserve">Refers to the material-only cost of replacing an entire fixture; labor cost is reported separately. This is used in the life cycle cost assessment, but is only used for the initial installation cost. Fixture replacement for maintenance should be built into the bulb replacement assumption. </v></c><c r="B104" s="913"/></row><row r="105" spans="1:2"><c r="A105" s="689"/><c r="B105" s="689"/></row><row r="106" spans="1:2"><c r="A106" s="689"/><c r="B106" s="689"/></row><row r="107" spans="1:2"><c r="A107" s="689"/><c r="B107" s="689"/></row><row r="108" spans="1:2"><c r="A108" s="689"/><c r="B108" s="689"/></row><row r="109" spans="1:2"><c r="A109" s="689"/><c r="B109" s="689"/></row><row r="110" spans="1:2"><c r="A110" s="689"/><c r="B110" s="689"/></row><row r="111" spans="1:2"><c r="A111" s="689"/><c r="B111" s="689"/></row><row r="112" spans="1:2"><c r="A112" s="689"/><c r="B112" s="689"/></row><row r="113" spans="1:2"><c r="A113" s="689"/><c r="B113" s="689"/></row><row r="114" spans="1:2"><c r="A114" s="689"/><c r="B114" s="689"/></row><row r="115" spans="1:2"><c r="A115" s="689"/><c r="B115" s="689"/></row><row r="116" spans="1:2"><c r="A116" s="689"/><c r="B116" s="689"/></row><row r="117" spans="1:2"><c r="A117" s="689"/><c r="B117" s="689"/></row><row r="118" spans="1:2"><c r="A118" s="689"/><c r="B118" s="689"/></row><row r="119" spans="1:2"><c r="A119" s="689"/><c r="B119" s="689"/></row><row r="120" spans="1:2"><c r="A120" s="689"/><c r="B120" s="689"/></row><row r="121" spans="1:2" ht="15.75" thickBot="1"><c r="A121" s="352" t="str"><f>Translation!B90</f><v>Fixture Life (hours)</v></c></row><row r="122" spans="1:2" ht="15.75" thickTop="1"/><row r="123" spans="1:2"><c r="A123" s="914" t="str"><f>Translation!B91</f><v xml:space="preserve">Fixture life is the assumed number of hours that the lamp can operate before the bulb needs replacing. This life corresponds to the assumed Replacement Bulb Cost for life cycle cost calculations. In the case of HPS fixtures, this life is of the bulb; the equipment cost of a bulb replacement is the typical cost of a bulb plus the average percent of fixtures that will also need to be replaced when bulb replacement occurs. In the case of LED fixtures, most manufacturers do not provide independent bulbs, so this refers to the life of the entire fixture. </v></c><c r="B123" s="914"/></row><row r="124" spans="1:2"><c r="A124" s="914" t="str"><f>Translation!B93</f><v>For LED fixtures , fixture life can be very long - but a poorly designed fixture may have a much shorter life than typical. It's very important to assess manufacturer claims about typical life. To assess these claims, here are some tips:</v></c><c r="B124" s="914"/></row><row r="125" spans="1:2" ht="30"><c r="B125" s="351" t="str"><f>Translation!B83</f><v xml:space="preserve"> - If TM 21 results are not available, ask for LM-80 test results, or comparable tests. This is the test method for determining LED depreciation at different junction temperatures. </v></c></row><row r="126" spans="1:2" ht="60"><c r="B126" s="351" t="str"><f>Translation!B84</f><v>- Ask the manufacturer to provide information about the junction temperature of their fixtures at different ambient outdoor temperatures. The biggest factor that reduces LED life is the temperature of the actual LED junction; a well designed fixture will be able to dissipate and have cooler junction temperatures.</v></c></row><row r="127" spans="1:2" ht="60"><c r="B127" s="351" t="str"><f>Translation!B86</f><v>-Additionally, ask for estimates of how fixture life will vary based on outdoor temperature. This is determined by combining information from LM-80 with the actual fixture design. While you may not be able to assess the accuracy of this information, it can provide an indication of how much the designer has thought about proper heat dissipation</v></c></row><row r="128" spans="1:2" ht="45"><c r="B128" s="351" t="str"><f>Translation!B85</f><v xml:space="preserve">- With long LED life, other electronic components in the fixture may fail before the LED's. To guard against this, ask about surge protection, water sealing, and any certification or testing on the electronic components in the fixture. </v></c></row><row r="153" spans="1:2"><c r="A153" s="689"/></row><row r="154" spans="1:2" ht="213.75" customHeight="1"><c r="A154" s="689"/><c r="B154" s="689"/></row><row r="155" spans="1:2"><c r="A155" s="689"/><c r="B155" s="689"/></row><row r="156" spans="1:2"><c r="A156" s="689"/><c r="B156" s="689"/></row><row r="157" spans="1:2"><c r="A157" s="689"/><c r="B157" s="689"/></row><row r="158" spans="1:2" ht="15.75" thickBot="1"><c r="A158" s="352" t="str"><f>Translation!B332</f><v>Number of Lanes</v></c><c r="B158" s="689"/></row><row r="159" spans="1:2" ht="30.75" thickTop="1"><c r="A159" s="688" t="str"><f>Translation!B333</f><v xml:space="preserve">Indicate the total number of lanes (both travel directions)
</v></c></row><row r="160" spans="1:2" ht="351" customHeight="1" thickBot="1"><c r="A160" s="352" t="str"><f>Translation!B334</f><v>Lane Width</v></c><c r="B160" s="688"/></row><row r="161" spans="1:2" ht="45.75" thickTop="1"><c r="A161" s="688" t="str"><f>Translation!B335</f><v xml:space="preserve">Indicate the width of each lane, in meters. All lanes are assumed to be the same width.
</v></c></row><row r="162" spans="1:2" s="350" customFormat="1" ht="177.75" customHeight="1"><c r="A162" s="688"/><c r="B162" s="688"/></row><row r="163" spans="1:2" s="350" customFormat="1"><c r="A163" s="688"/><c r="B163" s="688"/></row><row r="164" spans="1:2" s="350" customFormat="1"><c r="A164" s="688"/><c r="B164" s="688"/></row><row r="165" spans="1:2" s="350" customFormat="1"><c r="A165" s="688"/><c r="B165" s="688"/></row><row r="166" spans="1:2" s="350" customFormat="1"><c r="A166" s="688"/><c r="B166" s="688"/></row><row r="167" spans="1:2" s="350" customFormat="1"><c r="A167" s="688"/><c r="B167" s="688"/></row><row r="168" spans="1:2" s="350" customFormat="1"><c r="A168" s="688"/><c r="B168" s="688"/></row><row r="169" spans="1:2" s="350" customFormat="1"><c r="A169" s="688"/><c r="B169" s="688"/></row><row r="170" spans="1:2" s="350" customFormat="1"><c r="A170" s="688"/><c r="B170" s="688"/></row><row r="171" spans="1:2" s="350" customFormat="1"><c r="A171" s="688"/><c r="B171" s="688"/></row><row r="172" spans="1:2" s="350" customFormat="1"><c r="A172" s="688"/><c r="B172" s="688"/></row><row r="173" spans="1:2" s="350" customFormat="1"><c r="A173" s="688"/><c r="B173" s="688"/></row><row r="174" spans="1:2" s="350" customFormat="1"><c r="A174" s="688"/><c r="B174" s="688"/></row><row r="175" spans="1:2" s="350" customFormat="1"><c r="A175" s="688"/><c r="B175" s="688"/></row><row r="176" spans="1:2" s="350" customFormat="1"><c r="A176" s="688"/><c r="B176" s="688"/></row><row r="177" spans="1:2" s="350" customFormat="1"><c r="A177" s="688"/><c r="B177" s="688"/></row><row r="178" spans="1:2" s="350" customFormat="1" ht="15.75" thickBot="1"><c r="A178" s="352" t="str"><f>Translation!B336</f><v>Median Width</v></c><c r="B178" s="688"/></row><row r="179" spans="1:2" ht="30.75" thickTop="1"><c r="A179" s="689" t="str"><f>Translation!B337</f><v xml:space="preserve">Indicate the width of the median. If there is no median, use zero. 
</v></c></row><row r="180" spans="1:2" ht="160.5" customHeight="1"><c r="A180" s="689"/></row><row r="181" spans="1:2"><c r="A181" s="689"/></row><row r="182" spans="1:2"><c r="A182" s="689"/></row><row r="183" spans="1:2"><c r="A183" s="689"/></row><row r="184" spans="1:2"><c r="A184" s="689"/></row><row r="185" spans="1:2"><c r="A185" s="689"/></row><row r="186" spans="1:2"><c r="A186" s="689"/></row><row r="187" spans="1:2"><c r="A187" s="689"/></row><row r="188" spans="1:2"><c r="A188" s="689"/></row><row r="189" spans="1:2"><c r="A189" s="689"/></row><row r="190" spans="1:2"><c r="A190" s="689"/></row><row r="191" spans="1:2"><c r="A191" s="689"/></row><row r="192" spans="1:2"><c r="A192" s="689"/></row><row r="193" spans="1:2"><c r="A193" s="689"/></row><row r="194" spans="1:2"><c r="A194" s="689"/></row><row r="195" spans="1:2"><c r="A195" s="689"/></row><row r="196" spans="1:2"><c r="A196" s="689"/></row><row r="197" spans="1:2"><c r="A197" s="689"/></row><row r="198" spans="1:2"><c r="A198" s="689"/></row><row r="199" spans="1:2"><c r="A199" s="689"/></row><row r="200" spans="1:2" ht="15.75" thickBot="1"><c r="A200" s="352" t="str"><f>Translation!B338</f><v>Pole Placement</v></c></row><row r="201" spans="1:2" ht="180.75" thickTop="1"><c r="A201" s="688" t="str"><f>Translation!B339</f><v>Four pole placement configurations are provided: 

Single-sided: Poles placed on one side of the road only

Staggered: Poles placed on both sides of the road, with poles on the B side of the road located half way between the poles on the A side

Median: Two fixtures mounted on the same pole, located in the center of the median, each facing outward toward the travel lanes.

Opposite:  Poles are placed on both sides of the road exactly opposite to each other</v></c></row><row r="202" spans="1:2" ht="279.75" customHeight="1"><c r="A202" s="688"/><c r="B202" s="688"/></row><row r="203" spans="1:2"><c r="A203" s="688"/><c r="B203" s="688"/></row><row r="204" spans="1:2"><c r="A204" s="688"/><c r="B204" s="688"/></row><row r="205" spans="1:2"><c r="A205" s="688"/><c r="B205" s="688"/></row><row r="206" spans="1:2"><c r="A206" s="688"/><c r="B206" s="688"/></row><row r="207" spans="1:2"><c r="A207" s="688"/><c r="B207" s="688"/></row><row r="208" spans="1:2"><c r="A208" s="688"/><c r="B208" s="688"/></row><row r="209" spans="1:2"><c r="A209" s="688"/><c r="B209" s="688"/></row><row r="210" spans="1:2"><c r="A210" s="688"/><c r="B210" s="688"/></row><row r="211" spans="1:2"><c r="A211" s="688"/><c r="B211" s="688"/></row><row r="212" spans="1:2"><c r="A212" s="688"/><c r="B212" s="688"/></row><row r="213" spans="1:2"><c r="A213" s="688"/><c r="B213" s="688"/></row><row r="214" spans="1:2"><c r="A214" s="688"/><c r="B214" s="688"/></row><row r="215" spans="1:2"><c r="A215" s="688"/><c r="B215" s="688"/></row><row r="216" spans="1:2"><c r="A216" s="688"/><c r="B216" s="688"/></row><row r="217" spans="1:2"><c r="A217" s="688"/><c r="B217" s="688"/></row><row r="218" spans="1:2"><c r="A218" s="688"/><c r="B218" s="688"/></row><row r="219" spans="1:2"><c r="A219" s="688"/><c r="B219" s="688"/></row><row r="220" spans="1:2"><c r="A220" s="688"/><c r="B220" s="688"/></row><row r="221" spans="1:2"><c r="A221" s="688"/><c r="B221" s="688"/></row><row r="222" spans="1:2" ht="15.75" thickBot="1"><c r="A222" s="352" t="str"><f>Translation!B131</f><v>Luminaire Mounting Height</v></c><c r="B222" s="688"/></row><row r="223" spans="1:2" ht="180.75" thickTop="1"><c r="A223" s="688" t="str"><f>Translation!B340</f><v xml:space="preserve">Appropriate pole height depends on the surrounding area and road width. Narrow roads in residential areas tend to have lower pole heights, while wider roads with few nearby buildings have higher pole heights. When possible, higher pole heights are usually more cost effective as they allow wider pole spacing.  

Typical Heights:
Residential, 2 lane: 8 meters
Residential, 4 lane: 9 meters
Highway, 4 lane: 12 meters
Highway, 6 lane: 15 meters
</v></c></row><row r="224" spans="1:2" ht="228" customHeight="1"><c r="A224" s="688"/><c r="B224" s="688"/></row><row r="225" spans="1:2"><c r="A225" s="688"/><c r="B225" s="688"/></row><row r="226" spans="1:2"><c r="A226" s="688"/><c r="B226" s="688"/></row><row r="227" spans="1:2"><c r="A227" s="688"/><c r="B227" s="688"/></row><row r="228" spans="1:2"><c r="A228" s="688"/><c r="B228" s="688"/></row><row r="229" spans="1:2"><c r="A229" s="688"/><c r="B229" s="688"/></row><row r="230" spans="1:2"><c r="A230" s="688"/><c r="B230" s="688"/></row><row r="231" spans="1:2"><c r="A231" s="688"/><c r="B231" s="688"/></row><row r="232" spans="1:2"><c r="A232" s="688"/><c r="B232" s="688"/></row><row r="233" spans="1:2"><c r="A233" s="688"/><c r="B233" s="688"/></row><row r="234" spans="1:2"><c r="A234" s="688"/><c r="B234" s="688"/></row><row r="235" spans="1:2"><c r="A235" s="688"/><c r="B235" s="688"/></row><row r="236" spans="1:2"><c r="A236" s="688"/><c r="B236" s="688"/></row><row r="237" spans="1:2"><c r="A237" s="688"/><c r="B237" s="688"/></row><row r="238" spans="1:2"><c r="A238" s="688"/><c r="B238" s="688"/></row><row r="239" spans="1:2"><c r="A239" s="688"/><c r="B239" s="688"/></row><row r="240" spans="1:2"><c r="A240" s="688"/><c r="B240" s="688"/></row><row r="241" spans="1:2"><c r="A241" s="688"/><c r="B241" s="688"/></row><row r="242" spans="1:2"><c r="A242" s="688"/><c r="B242" s="688"/></row><row r="243" spans="1:2"><c r="A243" s="688"/><c r="B243" s="688"/></row><row r="244" spans="1:2" ht="15.75" thickBot="1"><c r="A244" s="352" t="str"><f>Translation!B341</f><v>Pole Spacing</v></c><c r="B244" s="688"/></row><row r="245" spans="1:2" ht="135.75" thickTop="1"><c r="A245" s="688" t="str"><f>Translation!B342</f><v xml:space="preserve">Pole spacing indicates the distance from the center of one pole to the center of the next pole. 

For single-side and median pole placements, this indicates the distance from pole to pole

For staggered configurations, this signifies the distance from one pole to the next pole on the same side of the road
</v></c><c r="B245" s="689"/></row><row r="246" spans="1:2" ht="269.25" customHeight="1"><c r="A246" s="688"/><c r="B246" s="688"/></row><row r="247" spans="1:2"><c r="A247" s="688"/><c r="B247" s="688"/></row><row r="248" spans="1:2"><c r="A248" s="688"/><c r="B248" s="688"/></row><row r="249" spans="1:2"><c r="A249" s="688"/><c r="B249" s="688"/></row><row r="250" spans="1:2"><c r="A250" s="688"/><c r="B250" s="688"/></row><row r="251" spans="1:2"><c r="A251" s="688"/><c r="B251" s="688"/></row><row r="252" spans="1:2"><c r="A252" s="688"/><c r="B252" s="688"/></row><row r="253" spans="1:2"><c r="A253" s="688"/><c r="B253" s="688"/></row><row r="254" spans="1:2"><c r="A254" s="688"/><c r="B254" s="688"/></row><row r="255" spans="1:2"><c r="A255" s="688"/><c r="B255" s="688"/></row><row r="256" spans="1:2"><c r="A256" s="688"/><c r="B256" s="688"/></row><row r="257" spans="1:2"><c r="A257" s="688"/><c r="B257" s="688"/></row><row r="258" spans="1:2"><c r="A258" s="688"/><c r="B258" s="688"/></row><row r="259" spans="1:2"><c r="A259" s="688"/><c r="B259" s="688"/></row><row r="260" spans="1:2"><c r="A260" s="688"/><c r="B260" s="688"/></row><row r="261" spans="1:2"><c r="A261" s="688"/><c r="B261" s="688"/></row><row r="262" spans="1:2"><c r="A262" s="688"/><c r="B262" s="688"/></row><row r="263" spans="1:2"><c r="A263" s="688"/><c r="B263" s="688"/></row><row r="264" spans="1:2"><c r="A264" s="688"/><c r="B264" s="688"/></row><row r="265" spans="1:2" ht="15.75" thickBot="1"><c r="A265" s="352" t="str"><f>Translation!B343</f><v>Pole Setback</v></c><c r="B265" s="688"/></row><row r="266" spans="1:2" ht="45.75" thickTop="1"><c r="A266" s="688" t="str"><f>Translation!B344</f><v xml:space="preserve">Distance from the pole mounting to the edge of the road. Only applies to single-side and staggered configurations. 
</v></c><c r="B266" s="689"/></row><row r="267" spans="1:2" ht="37.5" customHeight="1"><c r="A267" s="543"/><c r="B267" s="688"/></row><row r="268" spans="1:2"><c r="A268" s="543"/><c r="B268" s="543"/></row><row r="269" spans="1:2"><c r="A269" s="543"/><c r="B269" s="543"/></row><row r="270" spans="1:2"><c r="A270" s="543"/><c r="B270" s="543"/></row><row r="271" spans="1:2"><c r="A271" s="543"/><c r="B271" s="543"/></row><row r="272" spans="1:2"><c r="A272" s="543"/><c r="B272" s="543"/></row><row r="273" spans="1:2"><c r="A273" s="543"/><c r="B273" s="543"/></row><row r="274" spans="1:2"><c r="A274" s="543"/><c r="B274" s="543"/></row><row r="275" spans="1:2"><c r="A275" s="543"/><c r="B275" s="543"/></row><row r="276" spans="1:2"><c r="A276" s="543"/><c r="B276" s="543"/></row><row r="277" spans="1:2"><c r="A277" s="543"/><c r="B277" s="543"/></row><row r="278" spans="1:2"><c r="A278" s="543"/><c r="B278" s="543"/></row><row r="279" spans="1:2"><c r="A279" s="543"/><c r="B279" s="543"/></row><row r="280" spans="1:2"><c r="A280" s="543"/><c r="B280" s="543"/></row><row r="281" spans="1:2"><c r="A281" s="543"/><c r="B281" s="543"/></row><row r="282" spans="1:2"><c r="A282" s="543"/><c r="B282" s="543"/></row><row r="283" spans="1:2"><c r="A283" s="543"/><c r="B283" s="543"/></row><row r="284" spans="1:2"><c r="A284" s="543"/><c r="B284" s="543"/></row><row r="285" spans="1:2" ht="15.75" thickBot="1"><c r="A285" s="352" t="str"><f>Translation!B345</f><v>Arm Length</v></c><c r="B285" s="543"/></row><row r="286" spans="1:2" ht="45.75" thickTop="1"><c r="A286" s="688" t="str"><f>Translation!B557</f><v xml:space="preserve">Indicates the horizontal distance from the center of the pole mounting to the fixture centerline. This should include  half of the length of the fixture.
</v></c><c r="B286" s="689"/></row><row r="287" spans="1:2" ht="38.25" customHeight="1"><c r="A287" s="688"/><c r="B287" s="688"/></row><row r="288" spans="1:2"><c r="A288" s="688"/><c r="B288" s="688"/></row><row r="289" spans="1:2"><c r="A289" s="688"/><c r="B289" s="688"/></row><row r="290" spans="1:2"><c r="A290" s="688"/><c r="B290" s="688"/></row><row r="291" spans="1:2"><c r="A291" s="688"/><c r="B291" s="688"/></row><row r="292" spans="1:2"><c r="A292" s="688"/><c r="B292" s="688"/></row><row r="293" spans="1:2"><c r="A293" s="688"/><c r="B293" s="688"/></row><row r="294" spans="1:2"><c r="A294" s="688"/><c r="B294" s="688"/></row><row r="295" spans="1:2"><c r="A295" s="688"/><c r="B295" s="688"/></row><row r="296" spans="1:2"><c r="A296" s="688"/><c r="B296" s="688"/></row><row r="297" spans="1:2"><c r="A297" s="688"/><c r="B297" s="688"/></row><row r="298" spans="1:2"><c r="A298" s="688"/><c r="B298" s="688"/></row><row r="299" spans="1:2"><c r="A299" s="688"/><c r="B299" s="688"/></row><row r="300" spans="1:2"><c r="A300" s="688"/><c r="B300" s="688"/></row><row r="301" spans="1:2"><c r="A301" s="688"/><c r="B301" s="688"/></row><row r="302" spans="1:2"><c r="A302" s="688"/><c r="B302" s="688"/></row><row r="303" spans="1:2"><c r="A303" s="688"/><c r="B303" s="688"/></row><row r="304" spans="1:2"><c r="A304" s="688"/><c r="B304" s="688"/></row><row r="305" spans="1:2"><c r="A305" s="688"/><c r="B305" s="688"/></row><row r="306" spans="1:2"><c r="A306" s="688"/><c r="B306" s="688"/></row><row r="307" spans="1:2"><c r="A307" s="688"/><c r="B307" s="688"/></row><row r="308" spans="1:2" ht="15.75" thickBot="1"><c r="A308" s="354" t="str"><f>Translation!B346</f><v>Number of Points in Grid</v></c><c r="B308" s="688"/></row><row r="309" spans="1:2" ht="135.75" thickTop="1"><c r="A309" s="688" t="str"><f>Translation!B347</f><v xml:space="preserve">Indicates the number of measurement points from one pole to the next, with a measurement taken at two cross-road distances per lane. 

Max = 20

Per the IES calculation method, the number of points should be sufficient such that the Spacing of Grid is 5 meters, or 1/10 of the pole spacing whichever is less
</v></c><c r="B309" s="689"/></row><row r="310" spans="1:2" ht="24.75" customHeight="1"><c r="A310" s="688"/><c r="B310" s="688"/></row><row r="311" spans="1:2"><c r="A311" s="688"/><c r="B311" s="688"/></row><row r="312" spans="1:2"><c r="A312" s="688"/><c r="B312" s="688"/></row><row r="313" spans="1:2"><c r="A313" s="688"/><c r="B313" s="688"/></row><row r="314" spans="1:2"><c r="A314" s="688"/><c r="B314" s="688"/></row><row r="315" spans="1:2"><c r="A315" s="688"/><c r="B315" s="688"/></row><row r="316" spans="1:2"><c r="A316" s="688"/><c r="B316" s="688"/></row><row r="317" spans="1:2"><c r="A317" s="688"/><c r="B317" s="688"/></row><row r="318" spans="1:2"><c r="A318" s="688"/><c r="B318" s="688"/></row><row r="319" spans="1:2"><c r="A319" s="688"/><c r="B319" s="688"/></row><row r="320" spans="1:2"><c r="A320" s="688"/><c r="B320" s="688"/></row><row r="321" spans="1:2"><c r="A321" s="688"/><c r="B321" s="688"/></row><row r="322" spans="1:2"><c r="A322" s="688"/><c r="B322" s="688"/></row><row r="323" spans="1:2"><c r="A323" s="688"/><c r="B323" s="688"/></row><row r="324" spans="1:2"><c r="A324" s="688"/><c r="B324" s="688"/></row><row r="325" spans="1:2"><c r="A325" s="688"/><c r="B325" s="688"/></row><row r="326" spans="1:2"><c r="A326" s="688"/><c r="B326" s="688"/></row><row r="327" spans="1:2"><c r="A327" s="688"/><c r="B327" s="688"/></row><row r="328" spans="1:2"><c r="A328" s="688"/><c r="B328" s="688"/></row><row r="329" spans="1:2"><c r="A329" s="688"/><c r="B329" s="688"/></row><row r="330" spans="1:2"><c r="A330" s="688"/><c r="B330" s="688"/></row><row r="331" spans="1:2"><c r="A331" s="688"/><c r="B331" s="688"/></row><row r="332" spans="1:2" ht="15.75" thickBot="1"><c r="A332" s="354" t="str"><f>Translation!B352</f><v>Equipment Cost ($/fixture)</v></c><c r="B332" s="688"/></row><row r="333" spans="1:2" ht="60.75" thickTop="1"><c r="A333" s="688" t="str"><f>Translation!B353</f><v xml:space="preserve">This cost should be the all-in equipment cost for the fixture, including the fixture purchase cost, new arm if needed, and any other miscellaneous wiring or ballast costs. If this is your baseline fixture (i.e. already installed), the fixture cost should be zero. </v></c><c r="B333" s="689"/></row><row r="334" spans="1:2" ht="10.5" customHeight="1"><c r="A334" s="688"/><c r="B334" s="688"/></row><row r="335" spans="1:2"><c r="A335" s="688"/><c r="B335" s="688"/></row><row r="336" spans="1:2"><c r="A336" s="688"/><c r="B336" s="688"/></row><row r="337" spans="1:2"><c r="A337" s="688"/><c r="B337" s="688"/></row><row r="338" spans="1:2"><c r="A338" s="688"/><c r="B338" s="688"/></row><row r="339" spans="1:2"><c r="A339" s="688"/><c r="B339" s="688"/></row><row r="340" spans="1:2"><c r="A340" s="688"/><c r="B340" s="688"/></row><row r="341" spans="1:2"><c r="A341" s="688"/><c r="B341" s="688"/></row><row r="342" spans="1:2"><c r="A342" s="688"/><c r="B342" s="688"/></row><row r="343" spans="1:2"><c r="A343" s="688"/><c r="B343" s="688"/></row><row r="344" spans="1:2"><c r="A344" s="688"/><c r="B344" s="688"/></row><row r="345" spans="1:2"><c r="A345" s="688"/><c r="B345" s="688"/></row><row r="346" spans="1:2"><c r="A346" s="688"/><c r="B346" s="688"/></row><row r="347" spans="1:2"><c r="A347" s="688"/><c r="B347" s="688"/></row><row r="348" spans="1:2"><c r="A348" s="688"/><c r="B348" s="688"/></row><row r="349" spans="1:2"><c r="A349" s="688"/><c r="B349" s="688"/></row><row r="350" spans="1:2"><c r="A350" s="688"/><c r="B350" s="688"/></row><row r="351" spans="1:2"><c r="A351" s="688"/><c r="B351" s="688"/></row><row r="352" spans="1:2"><c r="A352" s="688"/><c r="B352" s="688"/></row><row r="353" spans="1:2"><c r="A353" s="688"/><c r="B353" s="688"/></row><row r="354" spans="1:2"><c r="A354" s="688"/><c r="B354" s="688"/></row><row r="355" spans="1:2" ht="15.75" thickBot="1"><c r="A355" s="354" t="str"><f>Translation!B354</f><v>One-time Rebate or Subsidy ($/fixture)</v></c><c r="B355" s="688"/></row><row r="356" spans="1:2" ht="30.75" thickTop="1"><c r="A356" s="688" t="str"><f>Translation!B355</f><v xml:space="preserve">Enter any rebates or subsidies to be removed from the overall equipment cost on a per fixture basis. </v></c><c r="B356" s="689"/></row><row r="357" spans="1:2" ht="43.5" customHeight="1"><c r="A357" s="688"/><c r="B357" s="688"/></row><row r="358" spans="1:2"><c r="A358" s="688"/><c r="B358" s="688"/></row><row r="359" spans="1:2"><c r="A359" s="688"/><c r="B359" s="688"/></row><row r="360" spans="1:2"><c r="A360" s="688"/><c r="B360" s="688"/></row><row r="361" spans="1:2"><c r="A361" s="688"/><c r="B361" s="688"/></row><row r="362" spans="1:2"><c r="A362" s="688"/><c r="B362" s="688"/></row><row r="363" spans="1:2"><c r="A363" s="688"/><c r="B363" s="688"/></row><row r="364" spans="1:2"><c r="A364" s="688"/><c r="B364" s="688"/></row><row r="365" spans="1:2"><c r="A365" s="688"/><c r="B365" s="688"/></row><row r="366" spans="1:2"><c r="A366" s="688"/><c r="B366" s="688"/></row><row r="367" spans="1:2"><c r="A367" s="688"/><c r="B367" s="688"/></row><row r="368" spans="1:2"><c r="A368" s="688"/><c r="B368" s="688"/></row><row r="369" spans="1:2"><c r="A369" s="688"/><c r="B369" s="688"/></row><row r="370" spans="1:2"><c r="A370" s="688"/><c r="B370" s="688"/></row><row r="371" spans="1:2"><c r="A371" s="688"/><c r="B371" s="688"/></row><row r="372" spans="1:2"><c r="A372" s="688"/><c r="B372" s="688"/></row><row r="373" spans="1:2"><c r="A373" s="688"/><c r="B373" s="688"/></row><row r="374" spans="1:2"><c r="A374" s="688"/><c r="B374" s="688"/></row><row r="375" spans="1:2"><c r="A375" s="688"/><c r="B375" s="688"/></row><row r="376" spans="1:2"><c r="A376" s="688"/><c r="B376" s="688"/></row><row r="377" spans="1:2" ht="15.75" thickBot="1"><c r="A377" s="354" t="str"><f>Translation!B356</f><v>Annual Maintenance Cost ($/year)</v></c><c r="B377" s="688"/></row><row r="378" spans="1:2" ht="90.75" thickTop="1"><c r="A378" s="688" t="str"><f>Translation!B357</f><v xml:space="preserve">The annual maintenance cost should reflect the cost of maintaining the fixtures and poles. This should include the cost of periodic relamping, cleaning (washing of LED fixtures), and repairs. It should include estimates of street or lane closures when relevant, on an average per fixture basis. For example, if 10% of your fixtures must be replaced every year, the maintenance cost would be 1/10 of the cost of replacing a single fixture. </v></c><c r="B378" s="689"/></row><row r="379" spans="1:2" ht="50.25" customHeight="1"><c r="A379" s="688"/><c r="B379" s="688"/></row><row r="380" spans="1:2"><c r="A380" s="688"/><c r="B380" s="688"/></row><row r="381" spans="1:2"><c r="A381" s="688"/><c r="B381" s="688"/></row><row r="382" spans="1:2"><c r="A382" s="688"/><c r="B382" s="688"/></row><row r="383" spans="1:2"><c r="A383" s="688"/><c r="B383" s="688"/></row><row r="384" spans="1:2"><c r="A384" s="688"/><c r="B384" s="688"/></row><row r="385" spans="1:2"><c r="A385" s="688"/><c r="B385" s="688"/></row><row r="386" spans="1:2"><c r="A386" s="688"/><c r="B386" s="688"/></row><row r="387" spans="1:2"><c r="A387" s="688"/><c r="B387" s="688"/></row><row r="388" spans="1:2"><c r="A388" s="688"/><c r="B388" s="688"/></row><row r="389" spans="1:2"><c r="A389" s="688"/><c r="B389" s="688"/></row><row r="390" spans="1:2"><c r="A390" s="688"/><c r="B390" s="688"/></row><row r="391" spans="1:2"><c r="A391" s="688"/><c r="B391" s="688"/></row><row r="392" spans="1:2"><c r="A392" s="688"/><c r="B392" s="688"/></row><row r="393" spans="1:2"><c r="A393" s="688"/><c r="B393" s="688"/></row><row r="394" spans="1:2"><c r="A394" s="688"/><c r="B394" s="688"/></row><row r="395" spans="1:2"><c r="A395" s="688"/><c r="B395" s="688"/></row><row r="396" spans="1:2"><c r="A396" s="688"/><c r="B396" s="688"/></row><row r="397" spans="1:2" ht="15.75" thickBot="1"><c r="A397" s="354" t="str"><f>Translation!B358</f><v>Maintenance inflation rate (%/year)</v></c><c r="B397" s="688"/></row><row r="398" spans="1:2" ht="30.75" thickTop="1"><c r="A398" s="688" t="str"><f>Translation!B359</f><v xml:space="preserve">Enter the estimated inflation rate of maintenance rates due to increased labor costs, etc. </v></c><c r="B398" s="689"/></row><row r="399" spans="1:2" ht="36" customHeight="1"><c r="A399" s="688"/><c r="B399" s="688"/></row><row r="400" spans="1:2"><c r="A400" s="688"/><c r="B400" s="688"/></row><row r="401" spans="1:2"><c r="A401" s="688"/><c r="B401" s="688"/></row><row r="402" spans="1:2"><c r="A402" s="688"/><c r="B402" s="688"/></row><row r="403" spans="1:2"><c r="A403" s="688"/><c r="B403" s="688"/></row><row r="404" spans="1:2"><c r="A404" s="688"/><c r="B404" s="688"/></row><row r="405" spans="1:2"><c r="A405" s="688"/><c r="B405" s="688"/></row><row r="406" spans="1:2"><c r="A406" s="688"/><c r="B406" s="688"/></row><row r="407" spans="1:2"><c r="A407" s="688"/><c r="B407" s="688"/></row><row r="408" spans="1:2"><c r="A408" s="688"/><c r="B408" s="688"/></row><row r="409" spans="1:2"><c r="A409" s="688"/><c r="B409" s="688"/></row><row r="410" spans="1:2"><c r="A410" s="688"/><c r="B410" s="688"/></row><row r="411" spans="1:2"><c r="A411" s="688"/><c r="B411" s="688"/></row><row r="412" spans="1:2"><c r="A412" s="688"/><c r="B412" s="688"/></row><row r="413" spans="1:2"><c r="A413" s="688"/><c r="B413" s="688"/></row><row r="414" spans="1:2"><c r="A414" s="688"/><c r="B414" s="688"/></row><row r="415" spans="1:2"><c r="A415" s="688"/><c r="B415" s="688"/></row><row r="416" spans="1:2"><c r="A416" s="688"/><c r="B416" s="688"/></row><row r="417" spans="1:2"><c r="A417" s="688"/><c r="B417" s="688"/></row><row r="418" spans="1:2" ht="15.75" thickBot="1"><c r="A418" s="354" t="str"><f>Translation!B360</f><v>Lamp Lumen Depreciation</v></c><c r="B418" s="688"/></row><row r="419" spans="1:2" ht="60.75" thickTop="1"><c r="A419" s="688" t="str"><f>Translation!B361</f><v xml:space="preserve">This value reflects the depreciation in light output due to fixture degradation as it ages. By entering a value here, you will discount the estimated light levels to base design on the future, degraded values, ensuring that the fixture still meet your lighting criteria at end of life. </v></c><c r="B419" s="689"/></row><row r="420" spans="1:2" ht="54.75" customHeight="1"><c r="A420" s="688"/><c r="B420" s="688"/></row><row r="421" spans="1:2"><c r="A421" s="688"/><c r="B421" s="688"/></row><row r="422" spans="1:2"><c r="A422" s="688"/><c r="B422" s="688"/></row><row r="423" spans="1:2"><c r="A423" s="688"/><c r="B423" s="688"/></row><row r="424" spans="1:2"><c r="A424" s="688"/><c r="B424" s="688"/></row><row r="425" spans="1:2"><c r="A425" s="688"/><c r="B425" s="688"/></row><row r="426" spans="1:2"><c r="A426" s="688"/><c r="B426" s="688"/></row><row r="427" spans="1:2"><c r="A427" s="688"/><c r="B427" s="688"/></row><row r="428" spans="1:2"><c r="A428" s="688"/><c r="B428" s="688"/></row><row r="429" spans="1:2"><c r="A429" s="688"/><c r="B429" s="688"/></row><row r="430" spans="1:2"><c r="A430" s="688"/><c r="B430" s="688"/></row><row r="431" spans="1:2"><c r="A431" s="688"/><c r="B431" s="688"/></row><row r="432" spans="1:2"><c r="A432" s="688"/><c r="B432" s="688"/></row><row r="433" spans="1:2"><c r="A433" s="688"/><c r="B433" s="688"/></row><row r="434" spans="1:2"><c r="A434" s="688"/><c r="B434" s="688"/></row><row r="435" spans="1:2"><c r="A435" s="688"/><c r="B435" s="688"/></row><row r="436" spans="1:2"><c r="A436" s="688"/><c r="B436" s="688"/></row><row r="437" spans="1:2"><c r="A437" s="688"/><c r="B437" s="688"/></row><row r="438" spans="1:2"><c r="A438" s="688"/><c r="B438" s="688"/></row><row r="439" spans="1:2" ht="15.75" thickBot="1"><c r="A439" s="354" t="str"><f>Translation!B362</f><v>Luminaire Dirt Depreciation (design year)</v></c><c r="B439" s="688"/></row><row r="440" spans="1:2" ht="60.75" thickTop="1"><c r="A440" s="688" t="str"><f>Translation!B363</f><v xml:space="preserve">Enter the fraction of light output that actually leaves the fixture when dirty. Fixture output can be reduced due to dirt, soot, etc. Typical values can be found in appropriate lighting standards based on the cleanliness of the air and environment. </v></c><c r="B440" s="689"/></row><row r="441" spans="1:2" ht="33" customHeight="1"><c r="A441" s="688"/><c r="B441" s="688"/></row><row r="442" spans="1:2"><c r="A442" s="688"/><c r="B442" s="688"/></row><row r="443" spans="1:2"><c r="A443" s="688"/><c r="B443" s="688"/></row><row r="444" spans="1:2"><c r="A444" s="688"/><c r="B444" s="688"/></row><row r="445" spans="1:2"><c r="A445" s="688"/><c r="B445" s="688"/></row><row r="446" spans="1:2"><c r="A446" s="688"/><c r="B446" s="688"/></row><row r="447" spans="1:2"><c r="A447" s="688"/><c r="B447" s="688"/></row><row r="448" spans="1:2"><c r="A448" s="688"/><c r="B448" s="688"/></row><row r="449" spans="1:2"><c r="A449" s="688"/><c r="B449" s="688"/></row><row r="450" spans="1:2"><c r="A450" s="688"/><c r="B450" s="688"/></row><row r="451" spans="1:2"><c r="A451" s="688"/><c r="B451" s="688"/></row><row r="452" spans="1:2"><c r="A452" s="688"/><c r="B452" s="688"/></row><row r="453" spans="1:2"><c r="A453" s="688"/><c r="B453" s="688"/></row><row r="454" spans="1:2"><c r="A454" s="688"/><c r="B454" s="688"/></row><row r="455" spans="1:2"><c r="A455" s="688"/><c r="B455" s="688"/></row><row r="456" spans="1:2"><c r="A456" s="688"/><c r="B456" s="688"/></row><row r="457" spans="1:2"><c r="A457" s="688"/><c r="B457" s="688"/></row><row r="458" spans="1:2"><c r="A458" s="688"/><c r="B458" s="688"/></row><row r="459" spans="1:2" ht="15.75" thickBot="1"><c r="A459" s="354" t="str"><f>Translation!B364</f><v>Desired fixture not available in the table below?</v></c><c r="B459" s="688"/></row><row r="460" spans="1:2" ht="30.75" thickTop="1"><c r="A460" s="688" t="str"><f>Translation!B365</f><v>IES files describe the light output of a fixture. You can obtain them from fixture manufacturers</v></c><c r="B460" s="689"/></row><row r="461" spans="1:2" ht="30" customHeight="1"><c r="A461" s="689"/><c r="B461" s="688"/></row><row r="462" spans="1:2"><c r="A462" s="365"/></row><row r="463" spans="1:2"><c r="A463" s="365"/></row><row r="464" spans="1:2"><c r="A464" s="365"/></row><row r="465" spans="1:1"><c r="A465" s="691"/></row><row r="466" spans="1:1"><c r="A466" s="365"/></row><row r="467" spans="1:1"><c r="A467" s="365"/></row><row r="468" spans="1:1"><c r="A468" s="365"/></row><row r="469" spans="1:1"><c r="A469" s="365"/></row><row r="470" spans="1:1"><c r="A470" s="365"/></row><row r="471" spans="1:1"><c r="A471" s="365"/></row><row r="472" spans="1:1"><c r="A472" s="365"/></row><row r="473" spans="1:1"><c r="A473" s="365"/></row><row r="474" spans="1:1"><c r="A474" s="365"/></row><row r="475" spans="1:1"><c r="A475" s="365"/></row><row r="476" spans="1:1"><c r="A476" s="365"/></row><row r="477" spans="1:1"><c r="A477" s="365"/></row><row r="478" spans="1:1"><c r="A478" s="365"/></row><row r="479" spans="1:1"><c r="A479" s="365"/></row><row r="480" spans="1:1"><c r="A480" s="365"/></row><row r="481" spans="1:1"><c r="A481" s="365"/></row><row r="482" spans="1:1"><c r="A482" s="365"/></row><row r="483" spans="1:1"><c r="A483" s="365"/></row><row r="484" spans="1:1"><c r="A484" s="365"/></row><row r="485" spans="1:1"><c r="A485" s="365"/></row><row r="486" spans="1:1"><c r="A486" s="365"/></row><row r="487" spans="1:1"><c r="A487" s="365"/></row><row r="488" spans="1:1"><c r="A488" s="365"/></row><row r="489" spans="1:1"><c r="A489" s="365"/></row><row r="490" spans="1:1"><c r="A490" s="365"/></row><row r="491" spans="1:1" ht="15.75" thickBot="1"><c r="A491" s="354" t="str"><f>Translation!B371</f><v>Energy Inflation Rate (%/year)</v></c></row><row r="492" spans="1:1" ht="15.75" thickTop="1"><c r="A492" s="365" t="str"><f>Translation!B577</f><v>The annual increase in nominal price of electricity.</v></c></row><row r="493" spans="1:1"><c r="A493" s="365"/></row><row r="494" spans="1:1"><c r="A494" s="365"/></row><row r="495" spans="1:1"><c r="A495" s="365"/></row><row r="496" spans="1:1"><c r="A496" s="365"/></row><row r="497" spans="1:1"><c r="A497" s="365"/></row><row r="498" spans="1:1"><c r="A498" s="365"/></row><row r="499" spans="1:1"><c r="A499" s="365"/></row><row r="500" spans="1:1"><c r="A500" s="365"/></row><row r="501" spans="1:1"><c r="A501" s="365"/></row><row r="502" spans="1:1"><c r="A502" s="365"/></row><row r="503" spans="1:1"><c r="A503" s="365"/></row><row r="504" spans="1:1"><c r="A504" s="365"/></row><row r="505" spans="1:1"><c r="A505" s="365"/></row><row r="506" spans="1:1"><c r="A506" s="365"/></row><row r="507" spans="1:1"><c r="A507" s="365"/></row><row r="508" spans="1:1"><c r="A508" s="365"/></row><row r="509" spans="1:1"><c r="A509" s="365"/></row><row r="510" spans="1:1"><c r="A510" s="365"/></row><row r="511" spans="1:1"><c r="A511" s="365"/></row><row r="512" spans="1:1"><c r="A512" s="365"/></row><row r="513" spans="1:1"><c r="A513" s="365"/></row><row r="514" spans="1:1"><c r="A514" s="365"/></row><row r="515" spans="1:1"><c r="A515" s="365"/></row><row r="516" spans="1:1"><c r="A516" s="365"/></row><row r="517" spans="1:1"><c r="A517" s="365"/></row><row r="518" spans="1:1"><c r="A518" s="365"/></row><row r="519" spans="1:1"><c r="A519" s="365"/></row><row r="520" spans="1:1"><c r="A520" s="365"/></row><row r="521" spans="1:1"><c r="A521" s="365"/></row><row r="522" spans="1:1"><c r="A522" s="365"/></row><row r="523" spans="1:1"><c r="A523" s="365"/></row><row r="524" spans="1:1"><c r="A524" s="365"/></row><row r="525" spans="1:1"><c r="A525" s="365"/></row><row r="526" spans="1:1"><c r="A526" s="365"/></row><row r="527" spans="1:1"><c r="A527" s="365"/></row><row r="528" spans="1:1"><c r="A528" s="365"/></row><row r="529" spans="1:1"><c r="A529" s="365"/></row><row r="530" spans="1:1"><c r="A530" s="365"/></row><row r="531" spans="1:1"><c r="A531" s="365"/></row><row r="532" spans="1:1"><c r="A532" s="365"/></row><row r="533" spans="1:1"><c r="A533" s="365"/></row><row r="534" spans="1:1"><c r="A534" s="365"/></row><row r="535" spans="1:1"><c r="A535" s="365"/></row><row r="536" spans="1:1"><c r="A536" s="365"/></row><row r="537" spans="1:1"><c r="A537" s="365"/></row><row r="538" spans="1:1"><c r="A538" s="365"/></row><row r="539" spans="1:1"><c r="A539" s="365"/></row><row r="540" spans="1:1"><c r="A540" s="365"/></row><row r="541" spans="1:1"><c r="A541" s="365"/></row><row r="542" spans="1:1"><c r="A542" s="365"/></row><row r="543" spans="1:1"><c r="A543" s="365"/></row><row r="544" spans="1:1"><c r="A544" s="365"/></row><row r="545" spans="1:1"><c r="A545" s="365"/></row><row r="546" spans="1:1"><c r="A546" s="365"/></row><row r="547" spans="1:1"><c r="A547" s="365"/></row><row r="548" spans="1:1"><c r="A548" s="365"/></row><row r="549" spans="1:1"><c r="A549" s="365"/></row><row r="550" spans="1:1"><c r="A550" s="365"/></row><row r="551" spans="1:1"><c r="A551" s="365"/></row><row r="552" spans="1:1"><c r="A552" s="365"/></row><row r="553" spans="1:1"><c r="A553" s="365"/></row><row r="554" spans="1:1"><c r="A554" s="365"/></row><row r="555" spans="1:1"><c r="A555" s="365"/></row><row r="556" spans="1:1"><c r="A556" s="365"/></row><row r="557" spans="1:1"><c r="A557" s="365"/></row><row r="558" spans="1:1"><c r="A558" s="365"/></row><row r="559" spans="1:1"><c r="A559" s="365"/></row><row r="560" spans="1:1"><c r="A560" s="365"/></row></sheetData><mergeCells count="13"><mergeCell ref="A15:B15"/><mergeCell ref="A123:B123"/><mergeCell ref="A124:B124"/><mergeCell ref="A31:B31"/><mergeCell ref="A33:B33"/><mergeCell ref="A53:B53"/><mergeCell ref="A68:B68"/><mergeCell ref="A76:B76"/><mergeCell ref="A81:B81"/><mergeCell ref="A69:B69"/><mergeCell ref="A104:B104"/><mergeCell ref="A88:B88"/><mergeCell ref="A94:B94"/></mergeCells><pageMargins left="0.7" right="0.7" top="0.75" bottom="0.75" header="0.3" footer="0.3"/><pageSetup orientation="portrait" r:id="rId1"/><drawing r:id="rId2"/></worksheet>